__init__.py
pusher_notification/__init__.py
pusher_notification/pusher_backend.py
tkaws/__init__.py
tkaws/tkathena.py
tkaws/tkdynamodb.py
tkaws/tkelasticsearch.py
tkaws/tkglue.py
tkaws/tkkinesis.py
tkaws/tklambda.py
tkaws/tkmongo.py
tkaws/tks3.py
tkaws/tkses.py
tkaws/tksns.py
tkaws/tksqs.py
tkemail/__init__.py
tkemail/tkemail.py
tkteams/__init__.py
tkapps_py_packages-0.1.14.dist-info/LICENSE
tkapps_py_packages-0.1.14.dist-info/METADATA
tkapps_py_packages-0.1.14.dist-info/WHEEL
tkapps_py_packages-0.1.14.dist-info/top_level.txt
tkapps_py_packages-0.1.14.dist-info/RECORD
