Metadata-Version: 2.1
Name: tkapps-py-packages
Version: 0.1.14
Summary: A common package to be used across multiple projects
Author-email: Gyan Ranjan <granjan@tekion.com>
Project-URL: Homepage, https://github.com/pypa/sampleproject
Project-URL: Bug Tracker, https://github.com/pypa/sampleproject/issues
Classifier: Programming Language :: Python :: 3
Classifier: License :: OSI Approved :: MIT License
Classifier: Operating System :: OS Independent
Requires-Python: >=3.7
License-File: LICENSE
Requires-Dist: pymongo
Requires-Dist: pusher
